wifind/__init__.py
wifind/__main__.py
wifind/_version.py
wifind/errors.py
wifind/learn.py
wifind/predict.py
wifind/rooms.py
wifind/scan.py
wifind/train.py
wifind/utils.py
wifind/watch.py
wifind-0.2.1.dist-info/LICENSE
wifind-0.2.1.dist-info/METADATA
wifind-0.2.1.dist-info/WHEEL
wifind-0.2.1.dist-info/entry_points.txt
wifind-0.2.1.dist-info/top_level.txt
wifind-0.2.1.dist-info/RECORD
