Metadata-Version: 2.1
Name: wifind
Version: 0.2.1
Summary: Wi-Fi indoor positioning system
Home-page: https://github.com/micheledinelli/wifind
Author: Dinelli Michele
Author-email: dinellimichele00@gmail.com
License: MIT
Platform: any
Classifier: Intended Audience :: Developers
Classifier: Intended Audience :: Customer Service
Classifier: Intended Audience :: System Administrators
Classifier: Operating System :: Microsoft
Classifier: Operating System :: MacOS :: MacOS X
Classifier: Operating System :: Unix
Classifier: Operating System :: POSIX
Classifier: Programming Language :: Python
Classifier: Topic :: Software Development
Classifier: Topic :: Software Development :: Libraries
Classifier: Topic :: Software Development :: Libraries :: Python Modules
Classifier: Topic :: System :: Software Distribution
Classifier: Topic :: System :: Systems Administration
Classifier: Topic :: Utilities
License-File: LICENSE
Requires-Dist: pandas
Requires-Dist: scikit-learn
Requires-Dist: access-points
